flytekitplugins_vaex-1.16.12-py3.14-nspkg.pth
flytekitplugins/vaex/__init__.py
flytekitplugins/vaex/sd_transformers.py
flytekitplugins_vaex-1.16.12.dist-info/METADATA
flytekitplugins_vaex-1.16.12.dist-info/WHEEL
flytekitplugins_vaex-1.16.12.dist-info/entry_points.txt
flytekitplugins_vaex-1.16.12.dist-info/namespace_packages.txt
flytekitplugins_vaex-1.16.12.dist-info/top_level.txt
flytekitplugins_vaex-1.16.12.dist-info/RECORD
