Metadata-Version: 2.4
Name: flytekitplugins-vaex
Version: 1.16.12
Summary: Vaex plugin for flytekit
Author: admin@flyte.org
License: apache2
Classifier: Intended Audience :: Science/Research
Classifier: Intended Audience :: Developers
Classifier: License :: OSI Approved :: Apache Software License
Classifier: Programming Language :: Python :: 3.9
Classifier: Programming Language :: Python :: 3.10
Classifier: Topic :: Scientific/Engineering
Classifier: Topic :: Scientific/Engineering :: Artificial Intelligence
Classifier: Topic :: Software Development
Classifier: Topic :: Software Development :: Libraries
Classifier: Topic :: Software Development :: Libraries :: Python Modules
Requires-Python: >=3.9
Requires-Dist: flytekit<2.0.0,>=1.3.0b2
Requires-Dist: vaex-core<4.14,>=4.13.0; python_version < "3.10"
Requires-Dist: vaex-core>=4.16.0; python_version >= "3.10"
Requires-Dist: pandas
Requires-Dist: pydantic<2.0
Dynamic: author
Dynamic: classifier
Dynamic: license
Dynamic: requires-dist
Dynamic: requires-python
Dynamic: summary
